{
  "id": "amzn-4mo2plg",
  "title": "Echo Video Meeting Studio Suite",
  "url": "https://amzn.to/4mo2plg",
  "price": "$127.60",
  "image": "https://source.unsplash.com/featured/600x400/?office-setup,gift&sig=plg",
  "rating": 4.7,
  "total_reviews": 4002,
  "features": [
    "Streamlines hybrid work setups in minutes",
    "Ergonomic touches keep focus high during long sessions",
    "Pairs with popular productivity apps and planners",
    "Loved by entrepreneurs and remote teams alike"
  ],
  "keywords": [
    "office",
    "work",
    "productivity",
    "desk",
    "remote work",
    "entrepreneur",
    "office gift",
    "productivity gear",
    "desk upgrade",
    "echo",
    "video meeting studio",
    "suite"
  ]
}
